CHANGES.rst
MANIFEST.in
README.rst
setup.cfg
setup.py
ActivityTracker.egg-info/PKG-INFO
ActivityTracker.egg-info/SOURCES.txt
ActivityTracker.egg-info/dependency_links.txt
ActivityTracker.egg-info/entry_points.txt
ActivityTracker.egg-info/top_level.txt
activitytracker/__init__.py
activitytracker/base.py
activitytracker/cli.py
activitytracker/tests.py
activitytracker/plugins/__init__.py
activitytracker/plugins/orgmode.py
activitytracker/plugins/text.py
activitytracker/plugins/tomboy.py