Metadata-Version: 1.0
Name: ActivityTracker
Version: 1.0
Summary: Task and time logging
Home-page: http://pypi.python.org/pypi/ActivityTracker
Author: Rocky Burt
Author-email: rocky@serverzen.com
License: UNKNOWN
Platform: UNKNOWN
